droughty/.ipynb_checkpoints/Untitled-Copy1-checkpoint.ipynb
droughty/.ipynb_checkpoints/Untitled-checkpoint.ipynb
droughty/.ipynb_checkpoints/Untitled1-checkpoint.ipynb
droughty/.python-version
droughty/__init__.py
droughty/cube_parser/__main__.py
droughty/cube_parser/cube.py
droughty/cube_parser/keys.py
droughty/cube_parser/lexer.py
droughty/cube_parser/parser.py
droughty/cube_parser/py.typed
droughty/cube_parser/simple.py
droughty/cube_parser/tokens.py
droughty/cube_parser/tree.py
droughty/cube_parser/utils.py
droughty/cube_parser/visitors.py
droughty/droughty_core/config.py
droughty/droughty_core/config_cli.py
droughty/droughty_core/droughty_data_prep.py
droughty/droughty_core/droughty_init.py
droughty/droughty_core/warehouse_target.py
droughty/droughty_cube/cube_base_dict.py
droughty/droughty_cube/cube_cli.py
droughty/droughty_cube/cube_explore_dict.py
droughty/droughty_cube/cube_explore_module.py
droughty/droughty_cube/cube_measure_module.py
droughty/droughty_cube/cube_module.py
droughty/droughty_dbml/dbml_base_dict.py
droughty/droughty_dbml/dbml_cli.py
droughty/droughty_dbml/dbml_module.py
droughty/droughty_dbt/.ipynb_checkpoints/Untitled-checkpoint.ipynb
droughty/droughty_dbt/dbt_test_base_dict.py
droughty/droughty_dbt/dbt_test_cli.py
droughty/droughty_dbt/dbt_test_field_base.py
droughty/droughty_dbt/dbt_test_module.py
droughty/droughty_docs/docs_cli.py
droughty/droughty_docs/openai_descriptions.py
droughty/droughty_jinjasql/jinjasql/__init__
droughty/droughty_jinjasql/jinjasql/core.py
droughty/droughty_lookml/lookml_base_dict.py
droughty/droughty_lookml/lookml_cli.py
droughty/droughty_lookml/lookml_explore_dict.py
droughty/droughty_lookml/lookml_explore_module.py
droughty/droughty_lookml/lookml_measure_module.py
droughty/droughty_lookml/lookml_module.py
droughty/droughty_lookml/lookml_pop_module.py
droughty/droughty_lookml/lookml_pop_module_snowflake.py
droughty/droughty_qa/qa_agent_base.py
droughty/droughty_qa/qa_agent_cli.py
droughty-0.20.1.dist-info/METADATA
droughty-0.20.1.dist-info/WHEEL
droughty-0.20.1.dist-info/entry_points.txt
droughty-0.20.1.dist-info/RECORD
