Metadata-Version: 2.4
Name: droughty
Version: 0.20.1
Summary: droughty is an analytics engineering toolkit, helping keep your workflow dry.
License: MIT
Author: lydia
Author-email: lydia@rittmananalytics.com
Requires-Python: >=3.9,<3.12.4
Classifier: License :: OSI Approved :: MIT License
Classifier: Programming Language :: Python :: 3
Classifier: Programming Language :: Python :: 3.9
Classifier: Programming Language :: Python :: 3.10
Classifier: Programming Language :: Python :: 3.11
Classifier: Programming Language :: Python :: 3.12
Provides-Extra: dedupe
Requires-Dist: GitPython (==3.1.44)
Requires-Dist: Markdown (==3.4.1)
Requires-Dist: PyYAML (==6.0.2)
Requires-Dist: glom (==23.1.1)
Requires-Dist: google-auth (>=2.28.1,<3.0.0)
Requires-Dist: jinja2 (==3.1.5)
Requires-Dist: langchain-core (>=0.3.30,<0.4.0)
Requires-Dist: langchain-openai (>=0.3.0,<0.4.0)
Requires-Dist: langgraph (>=0.2.64,<0.3.0)
Requires-Dist: langsmith (>=0.2.11,<0.3.0)
Requires-Dist: lkml (==1.3.1)
Requires-Dist: numpy (>=1.26.0,<2.0.0)
Requires-Dist: openai (==1.59.8)
Requires-Dist: ordereddict (==1.1)
Requires-Dist: pandas (>=2.2.0,<3.0.0)
Requires-Dist: pandas_dedupe (>=1.5.0,<2.0.0) ; extra == "dedupe"
Requires-Dist: pandas_gbq (>=0.20.0,<0.21.0)
Requires-Dist: protobuf (>=6.0,<7.0)
Requires-Dist: pyarrow (>=14.0.1,<19.0.0)
Requires-Dist: pydantic (>=2.10.5,<3.0.0)
Requires-Dist: ruamel-base (==1.0.0)
Requires-Dist: ruamel-yaml (==0.17.21)
Requires-Dist: six (==1.16.0)
Requires-Dist: snowflake-connector-python (>=3.13.0,<4.0.0)
Requires-Dist: snowflake-sqlalchemy (>=1.4.6,<2.0.0)
Requires-Dist: sqlalchemy (>=1.4.54,<2.0.0)
Requires-Dist: typing-extensions (==4.12.2)
Project-URL: Repository, https://github.com/rittmananalytics/droughty
